awsxmltojson/__init__.py
awsxmltojson/convert_xml_to_dict.py
awsxmltojson/get_shape.py
awsxmltojson/global_shapes.json
awsxmltojson/sqs-2012-11-05.normal.json
awsxmltojson/sqs_mappers.py
awsxmltojson/xml_etree_to_dict.py
awsxmltojson-0.2.3.dist-info/WHEEL
awsxmltojson-0.2.3.dist-info/METADATA
awsxmltojson-0.2.3.dist-info/RECORD
