Metadata-Version: 2.1
Name: awsxmltojson
Version: 0.2.3
Summary: Converts XML Responses from AWS API to JSON
Home-page: https://github.com/seveibar/awsxmltojson
License: MIT
Author: seveibar
Author-email: seveibar@gmail.com
Requires-Python: >=3.7,<4.0
Classifier: License :: OSI Approved :: MIT License
Classifier: Programming Language :: Python :: 3
Classifier: Programming Language :: Python :: 3.7
Classifier: Programming Language :: Python :: 3.8
Classifier: Programming Language :: Python :: 3.9
